{
  "version": 1,
  "active": true,
  "skill": "deep-interview",
  "keyword": "interview",
  "phase": "planning",
  "activated_at": "2026-04-24T06:42:08.015Z",
  "updated_at": "2026-04-24T06:52:57.237Z",
  "source": "keyword-detector",
  "session_id": "019db9fc-fcd7-76b0-8e37-d7b41a5097fa",
  "thread_id": "",
  "turn_id": "019dbe43-53c3-7dd3-bdd5-04ff14129aad",
  "active_skills": [
    {
      "skill": "deep-interview",
      "phase": "planning",
      "active": true,
      "activated_at": "2026-04-24T06:42:08.015Z",
      "updated_at": "2026-04-24T06:52:57.237Z",
      "session_id": "019db9fc-fcd7-76b0-8e37-d7b41a5097fa",
      "turn_id": "019dbe43-53c3-7dd3-bdd5-04ff14129aad",
      "thread_id": ""
    },
    {
      "skill": "ralph",
      "phase": "planning",
      "active": true,
      "activated_at": "2026-04-23T11:39:14.007Z",
      "updated_at": "2026-04-23T11:58:07.253Z",
      "session_id": "019db9fc-fcd7-76b0-8e37-d7b41a5097fa",
      "thread_id": "019dba22-7861-7193-b562-4c004b4476e0",
      "turn_id": "019dba22-8775-7502-960b-c34c6799dbbc"
    }
  ],
  "input_lock": {
    "active": true,
    "scope": "deep-interview-auto-approval",
    "acquired_at": "2026-04-24T06:42:08.015Z",
    "blocked_inputs": [
      "yes",
      "y",
      "proceed",
      "continue",
      "ok",
      "sure",
      "go ahead",
      "next i should"
    ],
    "message": "Deep interview is active; auto-approval shortcuts are blocked until the interview finishes."
  },
  "initialized_mode": "deep-interview",
  "initialized_state_path": ".omx/state/sessions/019db9fc-fcd7-76b0-8e37-d7b41a5097fa/deep-interview-state.json"
}